<?xml version="1.0" encoding="utf-8"?><toc><breadcrumbs><li><a href="f754febe-94bd-f878-9384-97a80885cf66.htm">Docs</a></li><li><a href="f754febe-94bd-f878-9384-97a80885cf66.htm">North<wbr />Lab.<wbr />Prefab<wbr />Drawer</a></li><li><a href="9ac4aa75-246e-370f-c374-7cff06f348e0.htm">Config</a></li></breadcrumbs><tocItems><li><a id="0357e243-4779-defa-8964-a4c14c1f7357" href="0357e243-4779-defa-8964-a4c14c1f7357.htm">Constructor</a></li><li><a id="657bb93d-4ed1-26c0-1413-d021252023cf" class="has-submenu" href="657bb93d-4ed1-26c0-1413-d021252023cf.htm"><span data-tocFile="../toc/IDBDA.xml" class="icon toggle" onclick="ToggleExpandCollapse(this); return false;"><i class="fa fa-angle-right"> </i></span>Properties</a><ul class="toc-menu is-hidden"> </ul></li><li><a id="102bd589-a3e6-9688-5cb4-2c4f724e3e3a" class="has-submenu" href="102bd589-a3e6-9688-5cb4-2c4f724e3e3a.htm"><span data-tocFile="../toc/IDCDA.xml" class="icon toggle" onclick="ToggleExpandCollapse(this); return false;"><i class="fa fa-angle-right"> </i></span>Methods</a><ul class="toc-menu is-hidden"> </ul></li></tocItems></toc>